aitsc/__init__.py
aitsc/main.py
ansible_inventory_to_ssh_config-1.1.2.dist-info/LICENSE
ansible_inventory_to_ssh_config-1.1.2.dist-info/METADATA
ansible_inventory_to_ssh_config-1.1.2.dist-info/WHEEL
ansible_inventory_to_ssh_config-1.1.2.dist-info/entry_points.txt
ansible_inventory_to_ssh_config-1.1.2.dist-info/top_level.txt
ansible_inventory_to_ssh_config-1.1.2.dist-info/RECORD
