Metadata-Version: 2.1
Name: ansible-inventory-to-ssh-config
Version: 1.1.2
Summary: Generate ssh config file from Ansible inventory
Author-email: Yioda <jyc180g@gmail.com>
Maintainer-email: Yioda <jyc180g@gmail.com>
License: MIT License
Project-URL: Homepage, https://github.com/yioda/ansible-inventory-to-ssh-config
Project-URL: Documentation, https://github.com/yioda/ansible-inventory-to-ssh-config
Project-URL: Repository, https://github.com/yioda/ansible-inventory-to-ssh-config.git
Keywords: egg,bacon,sausage,tomatoes,Lobster Thermidor
Classifier: Development Status :: 4 - Beta
Classifier: Programming Language :: Python
Requires-Python: >=3.8
License-File: LICENSE
Requires-Dist: ansible >=2.10.7
Requires-Dist: sshconf ==0.2.5
